japanese_address_parser_py-0.2.12.dist-info/METADATA
japanese_address_parser_py-0.2.12.dist-info/WHEEL
japanese_address_parser_py/__init__.py
japanese_address_parser_py/__init__.pyi
japanese_address_parser_py/py.typed
japanese_address_parser_py/japanese_address_parser_py.abi3.so
japanese_address_parser_py-0.2.12.dist-info/RECORD
