Metadata-Version: 2.4
Name: japanese-address-parser-py
Version: 0.2.12
Classifier: Topic :: Text Processing
Classifier: Programming Language :: Rust
Classifier: Typing :: Typed
Summary: A library for processing addresses of Japan
Keywords: converter,utility,geo,rust
Author: Yuuki Toriyama <github@toriyama.dev>
Author-email: Yuuki Toriyama <github@toriyama.dev>
License: MIT
Project-URL: Source Code, https://github.com/YuukiToriyama/japanese-address-parser
